zlcython/__init__.py
zlcython/__main__.py
zlcython/code.py
zlcython/coderun.py
zlcython/errentozh.py
zlcython/idle.py
zlcython/ifmaker.py
zlcython/install.py
zlcython/nple.py
zlcython/out.py
zlcython/runzlcython.py
zlcython/tes1__.py
zlcython/test1.py
zlcython/test_shell.py
zlcython/tran.py
zlcython-2.6.dist-info/LICENSE
zlcython-2.6.dist-info/METADATA
zlcython-2.6.dist-info/WHEEL
zlcython-2.6.dist-info/top_level.txt
zlcython-2.6.dist-info/RECORD
