Metadata-Version: 2.1
Name: zlcython
Version: 2.6
Summary: zlcython
Home-page: https://github.com/zlc1003/zlcython/
Author: zlc1001
Author-email: github.io@qq.com
Project-URL: Bug Tracker, https://github.com/zlc1003/zlcython/issues
Classifier: Programming Language :: Python :: 3
Classifier: License :: OSI Approved :: MIT License
Classifier: Operating System :: OS Independent
Requires-Python: >=3.6
License-File: LICENSE
